{
  "$schema": "https://mintlify.com/docs.json",
  "theme": "willow",
  "name": "Atlas CLI",
  "colors": {
    "primary": "#e6fb53",
    "light": "#f0fc63",
    "dark": "#c1de3e"
  },
  "favicon": "/favicon.svg",
  "logo": {
    "dark": "/logo-dark.svg",
    "light": "/logo-light.svg"
  },
  "navigation": {
    "tabs": [
      {
        "tab": "Documentation",
        "groups": [
          {
            "group": "Getting Started",
            "pages": ["introduction", "installation", "quickstart"]
          },
          {
            "group": "Commands",
            "pages": ["commands/upload", "commands/status", "commands/auth"]
          },
          {
            "group": "Advanced",
            "pages": ["advanced/parallel-uploads", "advanced/troubleshooting"]
          }
        ]
      }
    ]
  },
  "footerSocials": {
    "github": "https://github.com/arena-ai"
  },
  "feedback": {
    "thumbsRating": true
  },
  "modeToggle": {
    "default": "dark"
  }
}
